<?xml version="1.0" encoding="utf-8"?>
<!DOCTYPE hibernate-mapping PUBLIC "-//Hibernate/Hibernate Mapping DTD 3.0//EN"
"http://hibernate.sourceforge.net/hibernate-mapping-3.0.dtd">
<!-- 
    Mapping file autogenerated by MyEclipse Persistence Tools
-->
<hibernate-mapping>
    <class name="org.fudan.wuxi.syfw.model.hibentity.TraceInfo" table="trace_info" catalog="epcis_demo">
        <id name="epc" type="java.lang.String">
            <column name="epc" length="64" />
            <generator class="assigned" />
        </id>
        <property name="store" type="java.lang.String">
            <column name="store" length="64" />
        </property>
        <property name="dcName" type="java.lang.String">
            <column name="dcName" length="32" />
        </property>
        <property name="processingFac" type="java.lang.String">
            <column name="processingFac" length="32" />
        </property>
        <property name="bredingsiteName" type="java.lang.String">
            <column name="bredingsiteName" length="64" />
        </property>
        <property name="poolName" type="java.lang.String">
            <column name="poolName" length="32" />
        </property>
        <property name="aquticName" type="java.lang.String">
            <column name="aquticName" length="64" />
        </property>
        <property name="duraPeriod" type="java.lang.Integer">
            <column name="duraPeriod" precision="5" scale="0" />
        </property>
        <property name="storeEnv" type="java.lang.String">
            <column name="storeEnv" length="64" />
        </property>
        <property name="pondTime" type="java.sql.Date">
            <column name="pondTime" length="19" />
        </property>
        <property name="breedingBatchEpc" type="java.lang.String">
            <column name="breedingBatchEpc" length="64" />
        </property>
        <property name="inspector" type="java.lang.String">
            <column name="inspector" length="32" />
        </property>
        <property name="detcTime" type="java.sql.Date">
            <column name="detcTime" length="19" />
        </property>
        <property name="detcIndex" type="java.lang.String">
            <column name="detcIndex" length="32" />
        </property>
        <property name="detcResult" type="java.lang.String">
            <column name="detcResult" length="32" />
        </property>
        <property name="processingBatch" type="java.lang.String">
            <column name="processingBatch" length="32" />
        </property>
        <property name="processingFlow" type="java.lang.String">
            <column name="processingFlow" length="64" />
        </property>
        <property name="criticCtrPoint" type="java.lang.String">
            <column name="criticCtrPoint" length="64" />
        </property>
        <property name="deliveryTime" type="java.sql.Date">
            <column name="deliveryTime" length="19" />
        </property>
        <property name="deliveryBatchEpc" type="java.lang.String">
            <column name="deliveryBatchEpc" length="32" />
        </property>
    </class>
</hibernate-mapping>
